[
  { "nombre": "CAFÉ / CORTADO / LAGRIMA", "precio": 1500, "cat": "1. CAFETERÍA" },
  { "nombre": "CAFÉ DOBLE", "precio": 2500, "cat": "1. CAFETERÍA" },
  { "nombre": "TE", "precio": 1000, "cat": "1. CAFETERÍA" },
  { "nombre": "MEDIALUNA / TORTILLAS", "precio": 1000, "cat": "1. CAFETERÍA" },
  { "nombre": "FACTURA c/ Crema / CHURROS", "precio": 1200, "cat": "1. CAFETERÍA" },
  { "nombre": "CHIPA x 4 / ALFAJOR MAICENA", "precio": 2500, "cat": "1. CAFETERÍA" },
  { "nombre": "CRIOLLITOS x 3", "precio": 2500, "cat": "1. CAFETERÍA" },
  { "nombre": "⭐ PROMO: CAFÉ + 2 MEDIALUNAS", "precio": 4000, "cat": "1. CAFETERÍA" },
  { "nombre": "⭐ PROMO: CAFÉ DOBLE + MIXTO", "precio": 5000, "cat": "1. CAFETERÍA" },

  { "nombre": "COCA / SPRITE / FANTA / ZERO", "precio": 1000, "cat": "2. BEBIDAS SIN ALCOHOL" },
  { "nombre": "TÓNICA", "precio": 2500, "cat": "2. BEBIDAS SIN ALCOHOL" },
  { "nombre": "CITRIC", "precio": 2000, "cat": "2. BEBIDAS SIN ALCOHOL" },
  { "nombre": "AGUA BOTELLA", "precio": 1000, "cat": "2. BEBIDAS SIN ALCOHOL" },
  { "nombre": "SPEED", "precio": 3000, "cat": "2. BEBIDAS SIN ALCOHOL" },
  { "nombre": "LICUADO AGUA", "precio": 3600, "cat": "2. BEBIDAS SIN ALCOHOL" },
  { "nombre": "LICUADO LECHE", "precio": 4000, "cat": "2. BEBIDAS SIN ALCOHOL" },

  { "nombre": "PRECOCIDO JAMÓN Y QUESO", "precio": 5000, "cat": "3. SÁNDWICHERÍA" },
  { "nombre": "PRECOCIDO CRUDO Y QUESO", "precio": 5000, "cat": "3. SÁNDWICHERÍA" },
  { "nombre": "PRECOCIDO TERNERA, TOMATE Y QUESO", "precio": 5000, "cat": "3. SÁNDWICHERÍA" },
  { "nombre": "MIXTO JAMÓN Y QUESO", "precio": 3000, "cat": "3. SÁNDWICHERÍA" },
  { "nombre": "MIXTO TERNERA Y QUESO", "precio": 3000, "cat": "3. SÁNDWICHERÍA" },
  { "nombre": "MIXTO HUEVO / QUESO Y ACEITUNA", "precio": 3000, "cat": "3. SÁNDWICHERÍA" },
  { "nombre": "MIXTO ROQUEFORT Y PALETA", "precio": 3000, "cat": "3. SÁNDWICHERÍA" },
  { "nombre": "⭐ PROMO: PRECOCIDO + COCA", "precio": 5500, "cat": "3. SÁNDWICHERÍA" },
  { "nombre": "⭐ PROMO: MIXTO + COCA", "precio": 3500, "cat": "3. SÁNDWICHERÍA" },

  { "nombre": "EMPANADAS x 3", "precio": 4000, "cat": "4. EMPANADAS" },
  { "nombre": "⭐ PROMO: 3 EMPANADAS + GASEOSA", "precio": 4500, "cat": "4. EMPANADAS" },

  { "nombre": "GRANT'S", "precio": 3500, "cat": "5. BEBIDAS CON ALCOHOL" },
  { "nombre": "CHANDÓN GRANDE", "precio": 23000, "cat": "5. BEBIDAS CON ALCOHOL" },
  { "nombre": "NAVARRO CORREA", "precio": 18000, "cat": "5. BEBIDAS CON ALCOHOL" },
  { "nombre": "CHANDÓN 187", "precio": 7000, "cat": "5. BEBIDAS CON ALCOHOL" },
  { "nombre": "JOHNNIE WALKER ROJO", "precio": 5500, "cat": "5. BEBIDAS CON ALCOHOL" },
  { "nombre": "JOHNNIE WALKER NEGRO", "precio": 8000, "cat": "5. BEBIDAS CON ALCOHOL" },
  { "nombre": "FERNET CON COCA", "precio": 4000, "cat": "5. BEBIDAS CON ALCOHOL" },
  { "nombre": "HEINEKEN / CORONA", "precio": 5000, "cat": "5. BEBIDAS CON ALCOHOL" },
  { "nombre": "SALTA / QUILMES / BUDWEISER", "precio": 3500, "cat": "5. BEBIDAS CON ALCOHOL" },
  { "nombre": "GIN BOMBAY + TÓNICA", "precio": 6500, "cat": "5. BEBIDAS CON ALCOHOL" }
]
